kmcpy/__init__.py
kmcpy/_version.py
kmcpy/actually_executing_kmc.py
kmcpy/event.py
kmcpy/event_generator.py
kmcpy/fitting.py
kmcpy/io.py
kmcpy/kmc.py
kmcpy/making_structure_specific_files.py
kmcpy/model.py
kmcpy/tracker.py
kmcpy/external/cif.py
kmcpy/external/local_env.py
kmcpy/external/structure.py
kmcpy/store_tracker/tracker.py
kmcpy/tools/gather_kmc_data.py
kmcpy/tools/gather_mc_data.py
kmcpy/tools/get_data.py
kMCpy_victor-0.1.dev0.dist-info/METADATA
kMCpy_victor-0.1.dev0.dist-info/WHEEL
kMCpy_victor-0.1.dev0.dist-info/top_level.txt
kMCpy_victor-0.1.dev0.dist-info/RECORD
